{
  "type": "generic",
  "pools": [
    {
      "rolls": 1,
      "entries": [
        {
          "type": "item",
          "name": "stick",
          "weight": 2,
          "functions": [
            {
              "function": "set_nbt",
              "tag": "{CustomModelData:1,Enchant:{id:\"inaccuracy\",lvl:3s,\"Text\":'[{\"translate\":\"item.ui.enchantment.inaccuracy\",\"color\":\"red\",\"italic\":false},{\"text\":\" III: \",\"color\":\"red\",\"italic\":false},{\"text\":\"\uE010\",\"color\":\"white\",\"italic\":false},{\"translate\":\"item.ui.status.crt\",\"color\":\"gray\"},{\"text\":\" -20\",\"color\":\"red\"}]',Buffs:{atk:0,mag:0,tec:0,hp:0,int:0,def:0,spd:0,crt:-20,luk:0,conc:0}}}"
            }
          ],
          "conditions": [
            {
              "condition": "value_check",
              "value": {
                "type": "score",
                "target": "this",
                "score": "conc"
              },
              "range": 0
            }
          ]
        },
        {
          "type": "item",
          "name": "stick",
          "weight": 2,
          "functions": [
            {
              "function": "set_nbt",
              "tag": "{CustomModelData:1,Enchant:{id:\"inaccuracy\",lvl:2s,\"Text\":'[{\"translate\":\"item.ui.enchantment.inaccuracy\",\"color\":\"red\",\"italic\":false},{\"text\":\" II: \",\"color\":\"red\",\"italic\":false},{\"text\":\"\uE010\",\"color\":\"white\",\"italic\":false},{\"translate\":\"item.ui.status.crt\",\"color\":\"gray\"},{\"text\":\" -15\",\"color\":\"red\"}]',Buffs:{atk:0,mag:0,tec:0,hp:0,int:0,def:0,spd:0,crt:-15,luk:0,conc:0}}}"
            }
          ],
          "conditions": [
            {
              "condition": "value_check",
              "value": {
                "type": "score",
                "target": "this",
                "score": "conc"
              },
              "range": {
                "min": 0,
                "max": 10
              }
            }
          ]
        },
        {
          "type": "item",
          "name": "stick",
          "weight": 1,
          "functions": [
            {
              "function": "set_nbt",
              "tag": "{CustomModelData:1,Enchant:{id:\"inaccuracy\",lvl:1s,\"Text\":'[{\"translate\":\"item.ui.enchantment.inaccuracy\",\"color\":\"red\",\"italic\":false},{\"text\":\" I: \",\"color\":\"red\",\"italic\":false},{\"text\":\"\uE010\",\"color\":\"white\",\"italic\":false},{\"translate\":\"item.ui.status.crt\",\"color\":\"gray\"},{\"text\":\" -5\",\"color\":\"red\"}]',Buffs:{atk:0,mag:0,tec:0,hp:0,int:0,def:0,spd:0,crt:-5,luk:0,conc:0}}}"
            }
          ],
          "conditions": [
            {
              "condition": "value_check",
              "value": {
                "type": "score",
                "target": "this",
                "score": "conc"
              },
              "range": {
                "min": 0,
                "max": 15
              }
            }
          ]
        },
        {
          "type": "item",
          "name": "stick",
          "weight": 10,
          "functions": [
            {
              "function": "set_nbt",
              "tag": "{CustomModelData:1,Enchant:{id:\"critical_strike\",lvl:1s,\"Text\":'[{\"translate\":\"item.ui.enchantment.critical_strike\",\"color\":\"gray\",\"italic\":false},{\"text\":\" I: \",\"color\":\"gray\",\"italic\":false},{\"text\":\"\uE010\",\"color\":\"white\",\"italic\":false},{\"translate\":\"item.ui.status.crt\",\"color\":\"gray\"},{\"text\":\" +5\",\"color\":\"dark_green\"}]',Buffs:{atk:0,mag:0,tec:0,hp:0,int:0,def:0,spd:0,crt:5,luk:0,conc:0}}}"
            }
          ],
          "conditions": [
            {
              "condition": "value_check",
              "value": {
                "type": "score",
                "target": "this",
                "score": "conc"
              },
              "range": {
                "min": 0,
                "max": 30
              }
            }
          ]
        },
        {
          "type": "item",
          "name": "stick",
          "weight": 12,
          "functions": [
            {
              "function": "set_nbt",
              "tag": "{CustomModelData:1,Enchant:{id:\"critical_strike\",lvl:2s,\"Text\":'[{\"translate\":\"item.ui.enchantment.critical_strike\",\"color\":\"gray\",\"italic\":false},{\"text\":\" II: \",\"color\":\"gray\",\"italic\":false},{\"text\":\"\uE010\",\"color\":\"white\",\"italic\":false},{\"translate\":\"item.ui.status.crt\",\"color\":\"gray\"},{\"text\":\" +15\",\"color\":\"dark_green\"}]',Buffs:{atk:0,mag:0,tec:0,hp:0,int:0,def:0,spd:0,crt:15,luk:0,conc:0}}}"
            }
          ],
          "conditions": [
            {
              "condition": "value_check",
              "value": {
                "type": "score",
                "target": "this",
                "score": "conc"
              },
              "range": {
                "min": 20,
                "max": 40
              }
            }
          ]
        },
        {
          "type": "item",
          "name": "stick",
          "weight": 10,
          "functions": [
            {
              "function": "set_nbt",
              "tag": "{CustomModelData:1,Enchant:{id:\"critical_strike\",lvl:3s,\"Text\":'[{\"translate\":\"item.ui.enchantment.critical_strike\",\"color\":\"gray\",\"italic\":false},{\"text\":\" III: \",\"color\":\"gray\",\"italic\":false},{\"text\":\"\uE010\",\"color\":\"white\",\"italic\":false},{\"translate\":\"item.ui.status.crt\",\"color\":\"gray\"},{\"text\":\" +25\",\"color\":\"dark_green\"}]',Buffs:{atk:0,mag:0,tec:0,hp:0,int:0,def:0,spd:0,crt:25,luk:0,conc:0}}}"
            }
          ],
          "conditions": [
            {
              "condition": "value_check",
              "value": {
                "type": "score",
                "target": "this",
                "score": "conc"
              },
              "range": {
                "min": 30
              }
            }
          ]
        }
      ]
    }
  ]
}
